fesutils/__init__.py
fesutils/_cmdutils.py
fesutils/_containerutils.py
fesutils/_err_msg.py
fesutils/_oidutils.py
fesutils/_poolutils.py
fesutils/_strutils.py
fesutils/_timeparse.py
fesutils/_wraputils.py
fesutils/err.py
fesutils/parseutils.py
fesutils/schedutils.py
fesutils/cacheutils/__init__.py
fesutils/cacheutils/_cachelru.py
fesutils/cacheutils/_cacheutils.py
fesutils/schemautils/__init__.py
fesutils/schemautils/_fields.py
fesutils/schemautils/_schemautils.py
fesutils-1.1.3.dist-info/LICENSE
fesutils-1.1.3.dist-info/METADATA
fesutils-1.1.3.dist-info/WHEEL
fesutils-1.1.3.dist-info/top_level.txt
fesutils-1.1.3.dist-info/RECORD
