Metadata-Version: 2.1
Name: fesutils
Version: 1.1.3
Summary: 常用工具方法库
Home-page: https://github.com/tinybees/fesutils
Author: TinyBees
Author-email: a598824322@qq.com
License: MIT
Keywords: utils
Platform: UNKNOWN
Classifier: Development Status :: 5 - Production/Stable
Classifier: Intended Audience :: Developers
Classifier: License :: OSI Approved :: MIT License
Classifier: Natural Language :: Chinese (Simplified)
Classifier: Operating System :: POSIX :: Linux
Classifier: Operating System :: Microsoft :: Windows
Classifier: Operating System :: MacOS :: MacOS X
Classifier: Topic :: Software Development :: Libraries :: Python Modules
Classifier: Topic :: Utilities
Classifier: Programming Language :: Python
Classifier: Programming Language :: Python :: 3.6
Classifier: Programming Language :: Python :: 3.7
Classifier: Programming Language :: Python :: 3.8
Requires-Python: >=3.6
Requires-Dist: PyYAML (<=6.0.1,>=6.0)
Requires-Dist: aelog (<=1.0.9,>=1.0.6)
Requires-Dist: asyncio-contextmanager (==1.0.1)
Requires-Dist: marshmallow (<=3.14.1,>=3.0.1)
